WinBot/__init__.py
WinBot/__version__.py
WinBot/loguru_format.py
WinBot/main.py
WinBot/main_.py
WinBot.py-0.0.1.dist-info/LICENSE
WinBot.py-0.0.1.dist-info/METADATA
WinBot.py-0.0.1.dist-info/WHEEL
WinBot.py-0.0.1.dist-info/top_level.txt
WinBot.py-0.0.1.dist-info/RECORD
