Metadata-Version: 2.1
Name: WinBot.py
Version: 0.0.1
Summary: ...
Home-page: https://github.com/PyAibot/WinBot.git
Author: waitan2018
Maintainer: waitan2018
Requires-Python: >=3.6,<4.0
License-File: LICENSE
Requires-Dist: loguru (~=0.6.0)
